pq_oid/__init__.py
pq_oid-0.0.1.dist-info/METADATA
pq_oid-0.0.1.dist-info/WHEEL
pq_oid-0.0.1.dist-info/RECORD
